xmextras/__init__.py
xmextras/mcrlint.py
xmextras/noxm.py
xmextras/xm.py
xmextras-2024.291.949.dist-info/LICENSE.txt
xmextras-2024.291.949.dist-info/METADATA
xmextras-2024.291.949.dist-info/WHEEL
xmextras-2024.291.949.dist-info/entry_points.txt
xmextras-2024.291.949.dist-info/RECORD
